packscript.py
packscript-0.2.5.dist-info/licenses/LICENSE.txt
packscript-0.2.5.dist-info/METADATA
packscript-0.2.5.dist-info/WHEEL
packscript-0.2.5.dist-info/entry_points.txt
packscript-0.2.5.dist-info/top_level.txt
packscript-0.2.5.dist-info/RECORD
