Metadata-Version: 2.4
Name: packscript
Version: 0.2.5
Summary: A datapack compiler for Minecraft
Author: Slackow
License: MIT License
Project-URL: Repository, https://github.com/Slackow/PackScript.git
Project-URL: Issues, https://github.com/Slackow/PackScript/issues
Project-URL: Download, https://github.com/Slackow/PackScript/releases
Project-URL: Changelog, https://github.com/Slackow/PackScript/releases
Keywords: packscript,mcfunction,datapack,pack.mcmeta,nbt,templating,language
Requires-Python: >=3.12
License-File: LICENSE.txt
Dynamic: license-file
